MANIFEST.in
README.rst
setup.py
docs/HISTORY.txt
docs/LICENSE.GPL
docs/LICENSE.txt
ftw/__init__.py
ftw.bridge.client.egg-info/PKG-INFO
ftw.bridge.client.egg-info/SOURCES.txt
ftw.bridge.client.egg-info/dependency_links.txt
ftw.bridge.client.egg-info/entry_points.txt
ftw.bridge.client.egg-info/namespace_packages.txt
ftw.bridge.client.egg-info/not-zip-safe
ftw.bridge.client.egg-info/requires.txt
ftw.bridge.client.egg-info/top_level.txt
ftw/bridge/__init__.py
ftw/bridge/client/__init__.py
ftw/bridge/client/brain.py
ftw/bridge/client/config.py
ftw/bridge/client/configure.zcml
ftw/bridge/client/exceptions.py
ftw/bridge/client/hooks.py
ftw/bridge/client/interfaces.py
ftw/bridge/client/plugin.py
ftw/bridge/client/request.py
ftw/bridge/client/testing.py
ftw/bridge/client/utils.py
ftw/bridge/client/Extensions/install.py
ftw/bridge/client/browser/__init__.py
ftw/bridge/client/browser/catalog.py
ftw/bridge/client/browser/configure.zcml
ftw/bridge/client/browser/favorite.py
ftw/bridge/client/browser/recently_modified.pt
ftw/bridge/client/browser/watcher.py
ftw/bridge/client/browser/resources/bridge-client-compiled.js
ftw/bridge/client/browser/resources/main.js
ftw/bridge/client/browser/resources/watcher.js
ftw/bridge/client/locales/ftw.bridge.client.pot
ftw/bridge/client/locales/de/LC_MESSAGES/ftw.bridge.client.po
ftw/bridge/client/portlets/__init__.py
ftw/bridge/client/portlets/configure.zcml
ftw/bridge/client/portlets/watcher.py
ftw/bridge/client/portlets/templates/watcher.pt
ftw/bridge/client/portlets/templates/watcher_plone5.pt
ftw/bridge/client/profiles/default/jsregistry.xml
ftw/bridge/client/profiles/default/metadata.xml
ftw/bridge/client/profiles/default/portlets.xml
ftw/bridge/client/profiles/default/registry.xml
ftw/bridge/client/profiles/default_plone5/metadata.xml
ftw/bridge/client/profiles/default_plone5/portlets.xml
ftw/bridge/client/profiles/default_plone5/registry.xml
ftw/bridge/client/profiles/uninstall/jsregistry.xml
ftw/bridge/client/profiles/uninstall/portlets.xml
ftw/bridge/client/profiles/uninstall/registry.xml
ftw/bridge/client/profiles/uninstall_plone5/portlets.xml
ftw/bridge/client/profiles/uninstall_plone5/registry.xml
ftw/bridge/client/tabbed/__init__.py
ftw/bridge/client/tabbed/components.py
ftw/bridge/client/tabbed/configure.zcml
ftw/bridge/client/tabbed/interfaces.py
