Metadata-Version: 2.1
Name: ftw.bridge.client
Version: 1.1.1
Summary: Adds ftw.bridge support to plone.
Home-page: https://github.com/4teamwork/ftw.bridge.client
Author: 4teamwork AG
Author-email: mailto:info@4teamwork.ch
License: GPL2
Keywords: ftw bridge proxy client
Platform: UNKNOWN
Classifier: Framework :: Plone
Classifier: Framework :: Plone :: 4.1
Classifier: Framework :: Plone :: 4.2
Classifier: Framework :: Plone :: 4.3
Classifier: Framework :: Plone :: 5.1
Classifier: License :: OSI Approved :: GNU General Public License (GPL)
Classifier: Programming Language :: Python
Provides-Extra: tests
Provides-Extra: tabbedview
